dbis_btree/BBaum.py
dbis_btree/__init__.py
dbis_btree-1.0.8.dist-info/licenses/LICENCE
dbis_btree-1.0.8.dist-info/METADATA
dbis_btree-1.0.8.dist-info/WHEEL
dbis_btree-1.0.8.dist-info/top_level.txt
dbis_btree-1.0.8.dist-info/RECORD
