Metadata-Version: 2.4
Name: dbis-btree
Version: 1.0.8
Summary: RWTH Aachen Computer Science i5/dbis assets for Lecture Datenbanken und Informationssysteme
Author-email: DBIS i5 RWTH Aachen <dbis-vl@dbis.rwth-aachen.de>
Project-URL: Homepage, https://git.rwth-aachen.de/i5/teaching/dbis/dbis-btree
Classifier: Programming Language :: Python :: 3.10
Classifier: Programming Language :: Python :: 3.11
Classifier: Programming Language :: Python :: 3.12
Classifier: Programming Language :: Python :: 3.13
Requires-Python: >=3.10
License-File: LICENCE
Requires-Dist: numpy
Requires-Dist: graphviz
Requires-Dist: ipython
Provides-Extra: test
Requires-Dist: pytest; extra == "test"
Requires-Dist: pytest-cov; extra == "test"
Requires-Dist: tox; extra == "test"
Requires-Dist: black~=25.1.0; extra == "test"
Provides-Extra: lint
Requires-Dist: ruff; extra == "lint"
Provides-Extra: build
Requires-Dist: twine==6.*; extra == "build"
Requires-Dist: build==1.*; extra == "build"
Dynamic: license-file
